pyjac/__init__.py
pyjac/__main__.py
pyjac/_version.py
pyjac/utils.py
pyjac/core/CParams.py
pyjac/core/CUDAParams.py
pyjac/core/__init__.py
pyjac/core/cache_optimizer.py
pyjac/core/chem_utilities.py
pyjac/core/create_jacobian.py
pyjac/core/mech_auxiliary.py
pyjac/core/mech_interpret.py
pyjac/core/rate_subs.py
pyjac/core/shared_memory.py
pyjac/functional_tester/__init__.py
pyjac/functional_tester/__main__.py
pyjac/functional_tester/partially_stirred_reactor.py
pyjac/functional_tester/pasr_input.yaml
pyjac/functional_tester/test.py
pyjac/libgen/__init__.py
pyjac/libgen/__main__.py
pyjac/libgen/libgen.py
pyjac/performance_tester/__init__.py
pyjac/performance_tester/__main__.py
pyjac/performance_tester/fd_jacob.c
pyjac/performance_tester/fd_jacob.cu
pyjac/performance_tester/performance_tester.py
pyjac/performance_tester/read_initial_conditions.c
pyjac/performance_tester/read_initial_conditions.cu
pyjac/performance_tester/tc_tester.c.in
pyjac/performance_tester/tester.c.in
pyjac/performance_tester/tester.cu.in
pyjac/performance_tester/timer.h
pyjac/pywrap/__init__.py
pyjac/pywrap/__main__.py
pyjac/pywrap/adjacob_setup.py.in
pyjac/pywrap/adjacob_wrapper.pyx
pyjac/pywrap/parallel_compiler.py
pyjac/pywrap/py_tchem.c
pyjac/pywrap/py_tchem.h
pyjac/pywrap/pyjacob.cu
pyjac/pywrap/pyjacob.cuh
pyjac/pywrap/pyjacob_cuda_setup.py.in
pyjac/pywrap/pyjacob_cuda_wrapper.pyx
pyjac/pywrap/pyjacob_setup.py.in
pyjac/pywrap/pyjacob_wrapper.pyx
pyjac/pywrap/pytchem_setup.py.in
pyjac/pywrap/pytchem_wrapper.pyx
pyjac/pywrap/pywrap_gen.py
pyjac/tests/__init__.py
pyjac/tests/test_core.py
pyjac/tests/test_functional_tester.py
pyjac/tests/test_libgen.py
pyjac/tests/test_performance_tester.py
pyjac/tests/test_pywrap.py
pyjac/tests/test_utils.py
pyjac/tests/test_version.py
pyjac-1.0.6.dist-info/DESCRIPTION.rst
pyjac-1.0.6.dist-info/LICENSE.txt
pyjac-1.0.6.dist-info/METADATA
pyjac-1.0.6.dist-info/RECORD
pyjac-1.0.6.dist-info/WHEEL
pyjac-1.0.6.dist-info/entry_points.txt
pyjac-1.0.6.dist-info/metadata.json
pyjac-1.0.6.dist-info/top_level.txt
