Metadata-Version: 2.0
Name: pyjac
Version: 1.0.6
Summary: Create analytical Jacobian matrix source code for chemical kinetics
Home-page: https://github.com/slackha/pyJac
Author: Kyle E. Niemeyer
Author-email: kyle.niemeyer@gmail.com
License: MIT License
Keywords: chemical_kinetics analytical_Jacobian
Platform: UNKNOWN
Classifier: Development Status :: 5 - Production/Stable
Classifier: Intended Audience :: Developers
Classifier: Intended Audience :: Science/Research
Classifier: License :: OSI Approved :: MIT License
Classifier: Natural Language :: English
Classifier: Operating System :: OS Independent
Classifier: Programming Language :: Python :: 2
Classifier: Programming Language :: Python :: 2.7
Classifier: Programming Language :: Python :: 3
Classifier: Programming Language :: Python :: 3.4
Classifier: Programming Language :: Python :: 3.5
Classifier: Programming Language :: Python :: 3.6
Classifier: Topic :: Scientific/Engineering
Classifier: Topic :: Scientific/Engineering :: Physics
Classifier: Topic :: Software Development :: Libraries :: Python Modules
Requires-Dist: numpy (>=1.12.0)
Requires-Dist: bitarray (>=0.8.1)
Requires-Dist: optionloop (>1.0.3)
Requires-Dist: Cython (>=0.23.1)
Requires-Dist: pyyaml (>=3.11)
